{"stat.chestOpened":1,"stat.walkOneCm":64226,"stat.useItem.minecraft.torch":4,"stat.leaveGame":3,"stat.craftItem.minecraft.cooked_porkchop":1,"stat.furnaceInteraction":5,"stat.useItem.minecraft.cooked_porkchop":1,"stat.jump":249,"stat.swimOneCm":3008,"stat.useItem.minecraft.sand":1,"stat.fallOneCm":6301,"stat.crouchOneCm":971,"stat.sprintOneCm":25993,"achievement.exploreAllBiomes":{"value":0,"progress":["Extreme Hills+","Plains","Taiga","Extreme Hills"]},"achievement.openInventory":2,"stat.damageTaken":835,"stat.mineBlock.minecraft.torch":9,"stat.flyOneCm":35960,"stat.deaths":3,"stat.mineBlock.minecraft.leaves":12,"stat.mineBlock.minecraft.sand":1,"stat.playOneMinute":31945,"stat.timeSinceDeath":0,"stat.diveOneCm":7488}